dnaexchange/__init__.py
dnaexchange-0.0.1.dist-info/LICENSE.txt
dnaexchange-0.0.1.dist-info/METADATA
dnaexchange-0.0.1.dist-info/WHEEL
dnaexchange-0.0.1.dist-info/top_level.txt
dnaexchange-0.0.1.dist-info/RECORD
